planadversity/__init__.py
planadversity/manage_planadversity.py
planadversity/settings.py
planadversity/urls.py
planadversity/wsgi.py
planadversity/apps/__init__.py
planadversity/apps/meditations/.models.py.swp
planadversity/apps/meditations/__init__.py
planadversity/apps/meditations/__init__.pyc
planadversity/apps/meditations/admin.py
planadversity/apps/meditations/admin.pyc
planadversity/apps/meditations/forms.py
planadversity/apps/meditations/forms.pyc
planadversity/apps/meditations/models.py
planadversity/apps/meditations/models.pyc
planadversity/apps/meditations/tests.py
planadversity/apps/meditations/urls.py
planadversity/apps/meditations/urls.pyc
planadversity/apps/meditations/views.py
planadversity/apps/meditations/views.pyc
planadversity/apps/meditations/__pycache__/__init__.cpython-34.pyc
planadversity/apps/meditations/__pycache__/admin.cpython-34.pyc
planadversity/apps/meditations/__pycache__/forms.cpython-34.pyc
planadversity/apps/meditations/__pycache__/models.cpython-34.pyc
planadversity/apps/meditations/__pycache__/urls.cpython-34.pyc
planadversity/apps/meditations/__pycache__/views.cpython-34.pyc
planadversity/apps/proposals/.models.py.swp
planadversity/apps/proposals/__init__.py
planadversity/apps/proposals/__init__.pyc
planadversity/apps/proposals/admin.py
planadversity/apps/proposals/admin.pyc
planadversity/apps/proposals/context_processors.py
planadversity/apps/proposals/context_processors.pyc
planadversity/apps/proposals/forms.py
planadversity/apps/proposals/forms.pyc
planadversity/apps/proposals/models.py
planadversity/apps/proposals/models.pyc
planadversity/apps/proposals/org_urls.py
planadversity/apps/proposals/org_urls.pyc
planadversity/apps/proposals/tests.py
planadversity/apps/proposals/urls.py
planadversity/apps/proposals/urls.pyc
planadversity/apps/proposals/utils.py
planadversity/apps/proposals/utils.pyc
planadversity/apps/proposals/views.py
planadversity/apps/proposals/views.pyc
planadversity-1.0.2.dist-info/DESCRIPTION.rst
planadversity-1.0.2.dist-info/METADATA
planadversity-1.0.2.dist-info/RECORD
planadversity-1.0.2.dist-info/WHEEL
planadversity-1.0.2.dist-info/entry_points.txt
planadversity-1.0.2.dist-info/metadata.json
planadversity-1.0.2.dist-info/top_level.txt
