Metadata-Version: 2.0
Name: planadversity
Version: 1.0.2
Summary: An planadversity for django applications.
Home-page: http://gitlab.com/secstate/planadversity
Author: Colin Powell
Author-email: colin.powell@gmail.com
License: BSD
Platform: OS Independent
Classifier: Development Status :: 4 - Beta
Classifier: Framework :: Django
Classifier: Intended Audience :: Developers
Classifier: License :: OSI Approved :: BSD License
Classifier: Operating System :: OS Independent
Classifier: Programming Language :: Python
Classifier: Topic :: Internet :: WWW/HTTP
Classifier: Topic :: Internet :: WWW/HTTP :: Dynamic Content
Requires-Dist: Django (==1.9.2)
Requires-Dist: Pillow (==2.0.0)
Requires-Dist: boto (==2.39.0)
Requires-Dist: dj-database-url (==0.3.0)
Requires-Dist: django-allauth (==0.24.1)
Requires-Dist: django-bootstrap-form (==3.1)
Requires-Dist: django-braces (==1.4.0)
Requires-Dist: django-cache-url (==0.8.0)
Requires-Dist: django-configurations (==1.0)
Requires-Dist: django-cors-headers (==1.1.0)
Requires-Dist: django-custom-user (==0.5)
Requires-Dist: django-debug-toolbar (==1.4)
Requires-Dist: django-extensions (==1.6.1)
Requires-Dist: django-filter (==0.9.2)
Requires-Dist: django-floppyforms (==1.6.1)
Requires-Dist: django-localflavor (==1.1)
Requires-Dist: django-nose (==1.4.1)
Requires-Dist: django-storages (==1.1.8)
Requires-Dist: django-templated-email (==0.4.9)
Requires-Dist: djangorestframework (==3.3.2)
Requires-Dist: easy-thumbnails (==1.2)
Requires-Dist: factory-boy (==2.5.1)
Requires-Dist: gunicorn (==0.17.4)
Requires-Dist: markdown (==2.6.1)
Requires-Dist: psycopg2 (==2.5)
Requires-Dist: pylibmc (==1.5.0)
Requires-Dist: raven (==5.2.0)
Requires-Dist: setuptools (==18.0.1)
Requires-Dist: shortuuid (==0.4.2)
Requires-Dist: werkzeug (==0.11.4)
